{
  "name": "bergmite",
  "caption": "Bergmite",
  "types": [
    "ice"
  ],
  "num": 712,
  "baseStats": {
    "atk": 69,
    "def": 85,
    "hp": 55,
    "spa": 32,
    "spd": 35,
    "spe": 28
  },
  "gen": 6,
  "abilities": {
    "1": "own-tempo",
    "2": "ice-body",
    "H": "sturdy"
  },
  "evos": [
    "avalugg"
  ],
  "height": 1,
  "weight": 99.5,
  "learnset": [
    {
      "how": [
        "7T",
        "6T"
      ],
      "what": "after-you"
    },
    {
      "how": [
        "8M",
        "7M",
        "6M"
      ],
      "what": "attract"
    },
    {
      "how": [
        "8E"
      ],
      "what": "aurora-veil"
    },
    {
      "how": [
        "8M",
        "8L18",
        "7L39",
        "6L39"
      ],
      "what": "avalanche"
    },
    {
      "how": [
        "8L21",
        "7L1",
        "6L1"
      ],
      "what": "bite"
    },
    {
      "how": [
        "8M",
        "8L39",
        "7M",
        "7L43",
        "6M",
        "6L43"
      ],
      "what": "blizzard"
    },
    {
      "how": [
        "7M",
        "6M"
      ],
      "what": "confide"
    },
    {
      "how": [
        "8M",
        "8L33"
      ],
      "what": "crunch"
    },
    {
      "how": [
        "8L9",
        "7L22",
        "6L22"
      ],
      "what": "curse"
    },
    {
      "how": [
        "8L42",
        "7L49",
        "6L49"
      ],
      "what": "double-edge"
    },
    {
      "how": [
        "7M",
        "6M"
      ],
      "what": "double-team"
    },
    {
      "how": [
        "8M"
      ],
      "what": "endure"
    },
    {
      "how": [
        "8M",
        "7M",
        "6M"
      ],
      "what": "facade"
    },
    {
      "how": [
        "8M",
        "7M",
        "6M"
      ],
      "what": "flash-cannon"
    },
    {
      "how": [
        "7M",
        "6M"
      ],
      "what": "frost-breath"
    },
    {
      "how": [
        "8M",
        "7M",
        "6M"
      ],
      "what": "gyro-ball"
    },
    {
      "how": [
        "8M",
        "7M",
        "6M"
      ],
      "what": "hail"
    },
    {
      "how": [
        "8L1",
        "7L1",
        "6L1"
      ],
      "what": "harden"
    },
    {
      "how": [
        "8M",
        "7M",
        "6M"
      ],
      "what": "ice-beam"
    },
    {
      "how": [
        "8M",
        "8L24",
        "7L26",
        "6L26"
      ],
      "what": "ice-fang"
    },
    {
      "how": [
        "8M"
      ],
      "what": "icicle-spear"
    },
    {
      "how": [
        "8M",
        "8L12",
        "7T",
        "7L10",
        "6T",
        "6L10"
      ],
      "what": "icy-wind"
    },
    {
      "how": [
        "8M",
        "8L27",
        "7T",
        "6T"
      ],
      "what": "iron-defense"
    },
    {
      "how": [
        "8E",
        "7E",
        "6E"
      ],
      "what": "mirror-coat"
    },
    {
      "how": [
        "8E",
        "7E",
        "6E"
      ],
      "what": "mist"
    },
    {
      "how": [
        "8L6",
        "7L5",
        "6L5"
      ],
      "what": "powder-snow"
    },
    {
      "how": [
        "8M",
        "8L15",
        "7M",
        "6M"
      ],
      "what": "protect"
    },
    {
      "how": [
        "8M",
        "7M",
        "6M"
      ],
      "what": "rain-dance"
    },
    {
      "how": [
        "8L1",
        "7L35",
        "6L35"
      ],
      "what": "rapid-spin"
    },
    {
      "how": [
        "8L30",
        "7L47",
        "7E",
        "6L47",
        "6E"
      ],
      "what": "recover"
    },
    {
      "how": [
        "8M",
        "7M",
        "6M"
      ],
      "what": "rest"
    },
    {
      "how": [
        "7M",
        "6M"
      ],
      "what": "rock-polish"
    },
    {
      "how": [
        "8M",
        "7M",
        "6M"
      ],
      "what": "rock-slide"
    },
    {
      "how": [
        "6M"
      ],
      "what": "rock-smash"
    },
    {
      "how": [
        "8M",
        "7M",
        "6M"
      ],
      "what": "rock-tomb"
    },
    {
      "how": [
        "8M",
        "7M",
        "6M"
      ],
      "what": "round"
    },
    {
      "how": [
        "8M",
        "7M",
        "6M"
      ],
      "what": "safeguard"
    },
    {
      "how": [
        "8M",
        "7M",
        "6M"
      ],
      "what": "sleep-talk"
    },
    {
      "how": [
        "8M",
        "7T",
        "6T"
      ],
      "what": "snore"
    },
    {
      "how": [
        "8M",
        "7M",
        "6M"
      ],
      "what": "stone-edge"
    },
    {
      "how": [
        "6M"
      ],
      "what": "strength"
    },
    {
      "how": [
        "8M",
        "7M",
        "6M"
      ],
      "what": "substitute"
    },
    {
      "how": [
        "8M",
        "7M",
        "6M"
      ],
      "what": "surf"
    },
    {
      "how": [
        "7M",
        "6M"
      ],
      "what": "swagger"
    },
    {
      "how": [
        "8L3",
        "7L1",
        "6L1"
      ],
      "what": "tackle"
    },
    {
      "how": [
        "8L36",
        "7L15",
        "6L15"
      ],
      "what": "take-down"
    },
    {
      "how": [
        "7M",
        "6M"
      ],
      "what": "toxic"
    },
    {
      "how": [
        "7T",
        "6T"
      ],
      "what": "water-pulse"
    }
  ]
}
