{
  "id": 442,
  "name": "budew",
  "caption": "Budew",
  "types": [
    "grass",
    "poison"
  ],
  "num": 406,
  "gen": 4,
  "baseStats": {
    "atk": 30,
    "def": 35,
    "hp": 40,
    "spa": 50,
    "spd": 70,
    "spe": 55
  },
  "abilities": {
    "1": "natural-cure",
    "2": "poison-point",
    "H": "leaf-guard"
  },
  "evos": [
    "roselia"
  ],
  "height": 0.2,
  "weight": 1.2,
  "learnset": [
    {
      "how": [
        "8L1"
      ],
      "what": "absorb"
    },
    {
      "how": [
        "8M"
      ],
      "what": "attract"
    },
    {
      "how": [
        "8M"
      ],
      "what": "bullet-seed"
    },
    {
      "how": [
        "8E"
      ],
      "what": "cotton-spore"
    },
    {
      "how": [
        "8M"
      ],
      "what": "dazzling-gleam"
    },
    {
      "how": [
        "8M"
      ],
      "what": "endure"
    },
    {
      "how": [
        "8M"
      ],
      "what": "energy-ball"
    },
    {
      "how": [
        "8E"
      ],
      "what": "extrasensory"
    },
    {
      "how": [
        "8M"
      ],
      "what": "facade"
    },
    {
      "how": [
        "8M"
      ],
      "what": "giga-drain"
    },
    {
      "how": [
        "8M"
      ],
      "what": "grass-knot"
    },
    {
      "how": [
        "8L1"
      ],
      "what": "growth"
    },
    {
      "how": [
        "8M"
      ],
      "what": "leaf-storm"
    },
    {
      "how": [
        "8E"
      ],
      "what": "life-dew"
    },
    {
      "how": [
        "8M"
      ],
      "what": "pin-missile"
    },
    {
      "how": [
        "8M"
      ],
      "what": "protect"
    },
    {
      "how": [
        "8M"
      ],
      "what": "rain-dance"
    },
    {
      "how": [
        "8E"
      ],
      "what": "razor-leaf"
    },
    {
      "how": [
        "8M"
      ],
      "what": "rest"
    },
    {
      "how": [
        "8M"
      ],
      "what": "round"
    },
    {
      "how": [
        "8M"
      ],
      "what": "seed-bomb"
    },
    {
      "how": [
        "8M"
      ],
      "what": "shadow-ball"
    },
    {
      "how": [
        "8E"
      ],
      "what": "sleep-powder"
    },
    {
      "how": [
        "8M"
      ],
      "what": "sleep-talk"
    },
    {
      "how": [
        "8M"
      ],
      "what": "sludge-bomb"
    },
    {
      "how": [
        "8M"
      ],
      "what": "snore"
    },
    {
      "how": [
        "8M"
      ],
      "what": "solar-beam"
    },
    {
      "how": [
        "8M"
      ],
      "what": "spikes"
    },
    {
      "how": [
        "8L1"
      ],
      "what": "stun-spore"
    },
    {
      "how": [
        "8M"
      ],
      "what": "substitute"
    },
    {
      "how": [
        "8M"
      ],
      "what": "sunny-day"
    },
    {
      "how": [
        "8M"
      ],
      "what": "swift"
    },
    {
      "how": [
        "8M"
      ],
      "what": "swords-dance"
    },
    {
      "how": [
        "8E"
      ],
      "what": "synthesis"
    },
    {
      "how": [
        "8M"
      ],
      "what": "uproar"
    },
    {
      "how": [
        "8M"
      ],
      "what": "venoshock"
    },
    {
      "how": [
        "8M"
      ],
      "what": "weather-ball"
    },
    {
      "how": [
        "8L1"
      ],
      "what": "worry-seed"
    }
  ]
}
