{
  "name": "unfezant",
  "caption": "Unfezant",
  "types": [
    "normal",
    "flying"
  ],
  "num": 521,
  "baseStats": {
    "atk": 115,
    "def": 80,
    "hp": 80,
    "spa": 65,
    "spd": 55,
    "spe": 93
  },
  "gen": 5,
  "abilities": {
    "1": "big-pecks",
    "2": "super-luck",
    "H": "rivalry"
  },
  "prevo": "tranquill",
  "height": 1.2,
  "weight": 29,
  "learnset": [
    {
      "how": [
        "8M"
      ],
      "what": "agility"
    },
    {
      "how": [
        "8L16"
      ],
      "what": "air-cutter"
    },
    {
      "how": [
        "8M",
        "8L42"
      ],
      "what": "air-slash"
    },
    {
      "how": [
        "8M"
      ],
      "what": "attract"
    },
    {
      "how": [
        "8M"
      ],
      "what": "brave-bird"
    },
    {
      "how": [
        "8L36"
      ],
      "what": "detect"
    },
    {
      "how": [
        "8M"
      ],
      "what": "endure"
    },
    {
      "how": [
        "8M"
      ],
      "what": "facade"
    },
    {
      "how": [
        "8L26"
      ],
      "what": "feather-dance"
    },
    {
      "how": [
        "8M"
      ],
      "what": "fly"
    },
    {
      "how": [
        "8M"
      ],
      "what": "focus-energy"
    },
    {
      "how": [
        "8M"
      ],
      "what": "giga-impact"
    },
    {
      "how": [
        "8L1"
      ],
      "what": "growl"
    },
    {
      "how": [
        "8L1"
      ],
      "what": "gust"
    },
    {
      "how": [
        "8M"
      ],
      "what": "heat-wave"
    },
    {
      "how": [
        "8M"
      ],
      "what": "hurricane"
    },
    {
      "how": [
        "8M"
      ],
      "what": "hyper-beam"
    },
    {
      "how": [
        "8L1"
      ],
      "what": "leer"
    },
    {
      "how": [
        "8M"
      ],
      "what": "protect"
    },
    {
      "how": [
        "8L1"
      ],
      "what": "quick-attack"
    },
    {
      "how": [
        "8M"
      ],
      "what": "rain-dance"
    },
    {
      "how": [
        "8M"
      ],
      "what": "rest"
    },
    {
      "how": [
        "8L50"
      ],
      "what": "roost"
    },
    {
      "how": [
        "8M"
      ],
      "what": "round"
    },
    {
      "how": [
        "8L66"
      ],
      "what": "sky-attack"
    },
    {
      "how": [
        "8M"
      ],
      "what": "sleep-talk"
    },
    {
      "how": [
        "8M"
      ],
      "what": "snore"
    },
    {
      "how": [
        "8M"
      ],
      "what": "steel-wing"
    },
    {
      "how": [
        "8M"
      ],
      "what": "substitute"
    },
    {
      "how": [
        "8M"
      ],
      "what": "sunny-day"
    },
    {
      "how": [
        "8L20"
      ],
      "what": "swagger"
    },
    {
      "how": [
        "8M"
      ],
      "what": "swift"
    },
    {
      "how": [
        "8L58"
      ],
      "what": "tailwind"
    },
    {
      "how": [
        "8M",
        "8L12"
      ],
      "what": "taunt"
    },
    {
      "how": [
        "8M"
      ],
      "what": "uproar"
    },
    {
      "how": [
        "8M"
      ],
      "what": "u-turn"
    },
    {
      "how": [
        "8M"
      ],
      "what": "work-up"
    },
    {
      "how": [
        "8M"
      ],
      "what": "agility"
    },
    {
      "how": [
        "8L16"
      ],
      "what": "air-cutter"
    },
    {
      "how": [
        "8M",
        "8L38"
      ],
      "what": "air-slash"
    },
    {
      "how": [
        "8M"
      ],
      "what": "attract"
    },
    {
      "how": [
        "8L34"
      ],
      "what": "detect"
    },
    {
      "how": [
        "8M"
      ],
      "what": "endure"
    },
    {
      "how": [
        "8M"
      ],
      "what": "facade"
    },
    {
      "how": [
        "8L26"
      ],
      "what": "feather-dance"
    },
    {
      "how": [
        "8M"
      ],
      "what": "fly"
    },
    {
      "how": [
        "8M"
      ],
      "what": "focus-energy"
    },
    {
      "how": [
        "8L1"
      ],
      "what": "growl"
    },
    {
      "how": [
        "8L1"
      ],
      "what": "gust"
    },
    {
      "how": [
        "8M"
      ],
      "what": "heat-wave"
    },
    {
      "how": [
        "8L1"
      ],
      "what": "leer"
    },
    {
      "how": [
        "8M"
      ],
      "what": "protect"
    },
    {
      "how": [
        "8L1"
      ],
      "what": "quick-attack"
    },
    {
      "how": [
        "8M"
      ],
      "what": "rain-dance"
    },
    {
      "how": [
        "8M"
      ],
      "what": "rest"
    },
    {
      "how": [
        "8L44"
      ],
      "what": "roost"
    },
    {
      "how": [
        "8M"
      ],
      "what": "round"
    },
    {
      "how": [
        "8L56"
      ],
      "what": "sky-attack"
    },
    {
      "how": [
        "8M"
      ],
      "what": "sleep-talk"
    },
    {
      "how": [
        "8M"
      ],
      "what": "snore"
    },
    {
      "how": [
        "8M"
      ],
      "what": "steel-wing"
    },
    {
      "how": [
        "8M"
      ],
      "what": "substitute"
    },
    {
      "how": [
        "8M"
      ],
      "what": "sunny-day"
    },
    {
      "how": [
        "8L20"
      ],
      "what": "swagger"
    },
    {
      "how": [
        "8M"
      ],
      "what": "swift"
    },
    {
      "how": [
        "8L50"
      ],
      "what": "tailwind"
    },
    {
      "how": [
        "8M",
        "8L12"
      ],
      "what": "taunt"
    },
    {
      "how": [
        "8M"
      ],
      "what": "uproar"
    },
    {
      "how": [
        "8M"
      ],
      "what": "u-turn"
    },
    {
      "how": [
        "8M"
      ],
      "what": "work-up"
    },
    {
      "how": [
        "8M"
      ],
      "what": "agility"
    },
    {
      "how": [
        "8L16"
      ],
      "what": "air-cutter"
    },
    {
      "how": [
        "8M",
        "8L32"
      ],
      "what": "air-slash"
    },
    {
      "how": [
        "8M"
      ],
      "what": "attract"
    },
    {
      "how": [
        "8E"
      ],
      "what": "defog"
    },
    {
      "how": [
        "8L28"
      ],
      "what": "detect"
    },
    {
      "how": [
        "8M"
      ],
      "what": "endure"
    },
    {
      "how": [
        "8M"
      ],
      "what": "facade"
    },
    {
      "how": [
        "8L24"
      ],
      "what": "feather-dance"
    },
    {
      "how": [
        "8M"
      ],
      "what": "fly"
    },
    {
      "how": [
        "8M"
      ],
      "what": "focus-energy"
    },
    {
      "how": [
        "8L1"
      ],
      "what": "growl"
    },
    {
      "how": [
        "8L1"
      ],
      "what": "gust"
    },
    {
      "how": [
        "8M"
      ],
      "what": "heat-wave"
    },
    {
      "how": [
        "8E"
      ],
      "what": "hypnosis"
    },
    {
      "how": [
        "8L4"
      ],
      "what": "leer"
    },
    {
      "how": [
        "8E"
      ],
      "what": "morning-sun"
    },
    {
      "how": [
        "8E"
      ],
      "what": "night-slash"
    },
    {
      "how": [
        "8M"
      ],
      "what": "protect"
    },
    {
      "how": [
        "8L8"
      ],
      "what": "quick-attack"
    },
    {
      "how": [
        "8M"
      ],
      "what": "rain-dance"
    },
    {
      "how": [
        "8M"
      ],
      "what": "rest"
    },
    {
      "how": [
        "8L36"
      ],
      "what": "roost"
    },
    {
      "how": [
        "8M"
      ],
      "what": "round"
    },
    {
      "how": [
        "8L44"
      ],
      "what": "sky-attack"
    },
    {
      "how": [
        "8M"
      ],
      "what": "sleep-talk"
    },
    {
      "how": [
        "8M"
      ],
      "what": "snore"
    },
    {
      "how": [
        "8M"
      ],
      "what": "steel-wing"
    },
    {
      "how": [
        "8M"
      ],
      "what": "substitute"
    },
    {
      "how": [
        "8M"
      ],
      "what": "sunny-day"
    },
    {
      "how": [
        "8L20"
      ],
      "what": "swagger"
    },
    {
      "how": [
        "8M"
      ],
      "what": "swift"
    },
    {
      "how": [
        "8L40"
      ],
      "what": "tailwind"
    },
    {
      "how": [
        "8M",
        "8L12"
      ],
      "what": "taunt"
    },
    {
      "how": [
        "8M"
      ],
      "what": "uproar"
    },
    {
      "how": [
        "8M"
      ],
      "what": "u-turn"
    },
    {
      "how": [
        "8E"
      ],
      "what": "wish"
    },
    {
      "how": [
        "8M"
      ],
      "what": "work-up"
    }
  ]
}
