{
  "slug": "dynamicpunch",
  "name": "Dynamic Punch",
  "gen": 2,
  "type": "fighting",
  "category": "physical",
  "basePower": 100,
  "accuracy": 50,
  "pp": 5,
  "target": "normal",
  "priority": 0,
  "pokemon": [
    "breloom",
    "buzzwole",
    "cacnea",
    "cacturne",
    "conkeldurr",
    "crabominable",
    "crabrawler",
    "croagunk",
    "electabuzz",
    "electivire",
    "elekid",
    "golett",
    "golurk",
    "gurdurr",
    "hariyama",
    "machamp",
    "machoke",
    "machop",
    "magby",
    "magmar",
    "magmortar",
    "makuhita",
    "medicham",
    "meditite",
    "poliwrath",
    "timburr",
    "toxicroak"
  ],
  "desc": "Has a 100% chance to confuse the target.",
  "shortDesc": "100% chance to confuse the target."
}
