{
  "slug": "powerwhip",
  "name": "Power Whip",
  "gen": 4,
  "type": "grass",
  "category": "physical",
  "basePower": 120,
  "accuracy": 85,
  "pp": 10,
  "target": "normal",
  "priority": 0,
  "pokemon": [
    "bulbasaur",
    "ivysaur",
    "venusaur",
    "bellsprout",
    "weepinbell",
    "victreebel",
    "lickitung",
    "tangela",
    "roselia",
    "roserade",
    "carnivine",
    "lickilicky",
    "tangrowth",
    "ferrothorn",
    "goodra",
    "tsareena",
    "dhelmise",
    "xurkitree"
  ],
  "desc": "No additional effect.",
  "shortDesc": "No additional effect."
}
