{
  "slug": "tailwind",
  "name": "Tailwind",
  "gen": 4,
  "type": "flying",
  "category": "status",
  "pp": 15,
  "target": "allySide",
  "priority": 0,
  "pokemon": [
    "aerodactyl",
    "altaria",
    "arceus",
    "arceus-bug",
    "arceus-dark",
    "arceus-dragon",
    "arceus-electric",
    "arceus-fairy",
    "arceus-fighting",
    "arceus-fire",
    "arceus-flying",
    "arceus-ghost",
    "arceus-grass",
    "arceus-ground",
    "arceus-ice",
    "arceus-poison",
    "arceus-psychic",
    "arceus-rock",
    "arceus-steel",
    "arceus-water",
    "archen",
    "archeops",
    "articuno",
    "beautifly",
    "beedrill",
    "braviary",
    "butterfree",
    "castform",
    "charizard",
    "chatot",
    "combee",
    "comfey",
    "cottonee",
    "crobat",
    "cutiefly",
    "decidueye",
    "dragonite",
    "drampa",
    "drifblim",
    "drifloon",
    "ducklett",
    "dustox",
    "emolga",
    "farfetchd",
    "fearow",
    "finneon",
    "fletchinder",
    "fletchling",
    "flygon",
    "giratina",
    "giratina-origin",
    "gligar",
    "gliscor",
    "golbat",
    "hawlucha",
    "honchkrow",
    "hooh",
    "hoothoot",
    "hydreigon",
    "illumise",
    "kartana",
    "latias",
    "latios",
    "ledian",
    "ledyba",
    "lugia",
    "lumineon",
    "lunala",
    "mandibuzz",
    "mantine",
    "mantyke",
    "masquerain",
    "mew",
    "moltres",
    "mothim",
    "murkrow",
    "naganadel",
    "natu",
    "noctowl",
    "noibat",
    "noivern",
    "oricorio",
    "oricorio-pau",
    "oricorio-pompom",
    "oricorio-sensu",
    "pelipper",
    "pidgeot",
    "pidgeotto",
    "pidgey",
    "pidove",
    "pikipek",
    "rayquaza",
    "reshiram",
    "ribombee",
    "rufflet",
    "salamence",
    "scizor",
    "scyther",
    "shaymin",
    "shaymin-sky",
    "shiftry",
    "sigilyph",
    "silvally",
    "silvally-bug",
    "silvally-dark",
    "silvally-dragon",
    "silvally-electric",
    "silvally-fairy",
    "silvally-fighting",
    "silvally-fire",
    "silvally-flying",
    "silvally-ghost",
    "silvally-grass",
    "silvally-ground",
    "silvally-ice",
    "silvally-poison",
    "silvally-psychic",
    "silvally-rock",
    "silvally-steel",
    "silvally-water",
    "skarmory",
    "spearow",
    "staraptor",
    "staravia",
    "starly",
    "suicune",
    "swablu",
    "swanna",
    "swellow",
    "swoobat",
    "taillow",
    "talonflame",
    "togekiss",
    "togetic",
    "tornadus",
    "tornadus-therian",
    "toucannon",
    "tranquill",
    "tropius",
    "trumbeak",
    "unfezant",
    "venomoth",
    "vespiquen",
    "vibrava",
    "vivillon",
    "vivillon-fancy",
    "vivillon-pokeball",
    "volbeat",
    "volcarona",
    "vullaby",
    "whimsicott",
    "wingull",
    "woobat",
    "xatu",
    "yanma",
    "yanmega",
    "yveltal",
    "zapdos",
    "zekrom",
    "zubat"
  ],
  "desc": "For 4 turns, the user and its party members have their Speed doubled. Fails if this move is already in effect for the user's side.",
  "shortDesc": "For 4 turns, allies' Speed is doubled."
}
