{
  "slug": "politoed",
  "name": "Politoed",
  "num": 186,
  "types": [
    "water"
  ],
  "gen": 2,
  "abilities": {
    "0": "waterabsorb",
    "1": "damp",
    "H": "drizzle"
  },
  "baseStats": {
    "hp": 90,
    "atk": 75,
    "def": 75,
    "spa": 90,
    "spd": 100,
    "spe": 70
  },
  "prevo": "poliwhirl",
  "evoType": "trade",
  "evoItem": "King's Rock",
  "weight": 33.9,
  "height": 1.1,
  "genderRatio": {
    "M": 0.5,
    "F": 0.5
  },
  "eggGroups": [
    "Water 1"
  ],
  "learnset": {
    "amnesia": [
      "M"
    ],
    "bellydrum": [
      "L:1"
    ],
    "blizzard": [
      "M"
    ],
    "bodyslam": [
      "M",
      "L:1"
    ],
    "bounce": [
      "L:0"
    ],
    "brickbreak": [
      "M"
    ],
    "bubblebeam": [
      "L:1"
    ],
    "bulldoze": [
      "M"
    ],
    "chillingwater": [
      "M"
    ],
    "dig": [
      "M"
    ],
    "doubleedge": [
      "L:1"
    ],
    "earthpower": [
      "M",
      "L:1"
    ],
    "earthquake": [
      "M"
    ],
    "encore": [
      "M"
    ],
    "endeavor": [
      "E@poliwag"
    ],
    "endure": [
      "M"
    ],
    "facade": [
      "M"
    ],
    "fling": [
      "M"
    ],
    "focusblast": [
      "M"
    ],
    "focuspunch": [
      "M"
    ],
    "gigaimpact": [
      "M"
    ],
    "haze": [
      "M"
    ],
    "helpinghand": [
      "M"
    ],
    "hydropump": [
      "M",
      "L:1"
    ],
    "hyperbeam": [
      "M"
    ],
    "hypervoice": [
      "M",
      "L:1"
    ],
    "hypnosis": [
      "L:1"
    ],
    "icebeam": [
      "M"
    ],
    "icepunch": [
      "M"
    ],
    "icywind": [
      "M"
    ],
    "liquidation": [
      "M"
    ],
    "lowkick": [
      "M"
    ],
    "lowsweep": [
      "M"
    ],
    "metronome": [
      "M"
    ],
    "mist": [
      "E@poliwag"
    ],
    "muddywater": [
      "E@poliwag"
    ],
    "mudshot": [
      "M",
      "L:1"
    ],
    "mudslap": [
      "M"
    ],
    "perishsong": [
      "L:1"
    ],
    "pound": [
      "L:1"
    ],
    "protect": [
      "M"
    ],
    "psychic": [
      "M"
    ],
    "raindance": [
      "M",
      "L:1"
    ],
    "rest": [
      "M"
    ],
    "sleeptalk": [
      "M"
    ],
    "splash": [
      "E@poliwag"
    ],
    "substitute": [
      "M"
    ],
    "surf": [
      "M"
    ],
    "swagger": [
      "L:1"
    ],
    "swift": [
      "M"
    ],
    "takedown": [
      "M"
    ],
    "terablast": [
      "M"
    ],
    "thief": [
      "M"
    ],
    "waterfall": [
      "M"
    ],
    "watergun": [
      "L:1"
    ],
    "waterpulse": [
      "M",
      "E@poliwag"
    ],
    "weatherball": [
      "M"
    ]
  }
}
