{
  "slug": "zacian-crowned",
  "name": "Zacian",
  "subName": "Crowned Sword",
  "num": 888,
  "types": [
    "fairy",
    "steel"
  ],
  "gen": 8,
  "abilities": {
    "0": "intrepidsword"
  },
  "baseStats": {
    "hp": 92,
    "atk": 150,
    "def": 115,
    "spa": 80,
    "spd": 115,
    "spe": 148
  },
  "baseSpecies": "zacian",
  "formeTriggerItem": "rustedsword",
  "isBattleOnly": true,
  "weight": 355,
  "height": 2.8,
  "gender": "N",
  "eggGroups": [
    "Undiscovered"
  ],
  "isLegendary": true,
  "learnset": {
    "agility": [
      "M"
    ],
    "airslash": [
      "M"
    ],
    "behemothblade": [
      "R"
    ],
    "bite": [
      "L:1"
    ],
    "bodyslam": [
      "M"
    ],
    "brickbreak": [
      "M"
    ],
    "closecombat": [
      "M",
      "L:77"
    ],
    "crunch": [
      "M",
      "L:55"
    ],
    "dazzlinggleam": [
      "M"
    ],
    "dig": [
      "M"
    ],
    "endure": [
      "M"
    ],
    "facade": [
      "M"
    ],
    "falseswipe": [
      "M"
    ],
    "firefang": [
      "M"
    ],
    "flashcannon": [
      "M"
    ],
    "focusblast": [
      "M"
    ],
    "gigaimpact": [
      "M",
      "L:88"
    ],
    "helpinghand": [
      "M"
    ],
    "howl": [
      "L:1"
    ],
    "hyperbeam": [
      "M"
    ],
    "hypervoice": [
      "M"
    ],
    "icefang": [
      "M"
    ],
    "imprison": [
      "M"
    ],
    "irondefense": [
      "M"
    ],
    "ironhead": [
      "M",
      "L:33"
    ],
    "metalclaw": [
      "M",
      "L:1"
    ],
    "mistyterrain": [
      "M"
    ],
    "moonblast": [
      "L:66"
    ],
    "nobleroar": [
      "L:44"
    ],
    "playrough": [
      "M"
    ],
    "poisonjab": [
      "M"
    ],
    "protect": [
      "M"
    ],
    "psychicfangs": [
      "M"
    ],
    "quickattack": [
      "L:1"
    ],
    "quickguard": [
      "L:1"
    ],
    "rest": [
      "M"
    ],
    "reversal": [
      "M"
    ],
    "sacredsword": [
      "L:1"
    ],
    "scaryface": [
      "M"
    ],
    "slash": [
      "L:11"
    ],
    "sleeptalk": [
      "M"
    ],
    "snarl": [
      "M"
    ],
    "steelbeam": [
      "M"
    ],
    "substitute": [
      "M"
    ],
    "swift": [
      "M"
    ],
    "swordsdance": [
      "M",
      "L:22"
    ],
    "takedown": [
      "M"
    ],
    "terablast": [
      "M"
    ],
    "thunderfang": [
      "M"
    ],
    "trailblaze": [
      "M"
    ],
    "wildcharge": [
      "M"
    ]
  }
}
