{
  "slug": "litleo",
  "name": "Litleo",
  "num": 667,
  "types": [
    "fire",
    "normal"
  ],
  "gen": 6,
  "abilities": {
    "0": "rivalry",
    "1": "unnerve",
    "H": "moxie"
  },
  "baseStats": {
    "hp": 62,
    "atk": 50,
    "def": 58,
    "spa": 73,
    "spd": 54,
    "spe": 72
  },
  "evos": [
    "pyroar"
  ],
  "formeIndex": 0,
  "weight": 13.5,
  "height": 0.6,
  "genderRatio": {
    "M": 0.125,
    "F": 0.875
  },
  "eggGroups": [
    "Field"
  ],
  "canHatch": true,
  "learnset": {
    "attract": [
      "M"
    ],
    "bulldoze": [
      "M"
    ],
    "confide": [
      "M"
    ],
    "crunch": [
      "L:39"
    ],
    "darkpulse": [
      "M"
    ],
    "dig": [
      "M"
    ],
    "doubleteam": [
      "M"
    ],
    "echoedvoice": [
      "M",
      "L:33"
    ],
    "ember": [
      "L:5"
    ],
    "endeavor": [
      "T",
      "L:28"
    ],
    "entrainment": [
      "E"
    ],
    "facade": [
      "M"
    ],
    "fireblast": [
      "M"
    ],
    "firefang": [
      "L:23"
    ],
    "firespin": [
      "E"
    ],
    "flamecharge": [
      "M"
    ],
    "flamethrower": [
      "M",
      "L:36"
    ],
    "frustration": [
      "M"
    ],
    "headbutt": [
      "L:11"
    ],
    "heatwave": [
      "T"
    ],
    "helpinghand": [
      "T"
    ],
    "hiddenpower": [
      "M"
    ],
    "hypervoice": [
      "T",
      "L:43"
    ],
    "incinerate": [
      "M",
      "L:46"
    ],
    "irontail": [
      "T"
    ],
    "leer": [
      "L:1"
    ],
    "nobleroar": [
      "L:15"
    ],
    "overheat": [
      "M",
      "L:50"
    ],
    "payback": [
      "M"
    ],
    "protect": [
      "M"
    ],
    "raindance": [
      "M"
    ],
    "rest": [
      "M"
    ],
    "retaliate": [
      "M"
    ],
    "return": [
      "M"
    ],
    "roar": [
      "M"
    ],
    "rocksmash": [
      "M"
    ],
    "round": [
      "M"
    ],
    "secretpower": [
      "M"
    ],
    "sleeptalk": [
      "M"
    ],
    "snarl": [
      "M"
    ],
    "snatch": [
      "T",
      "E"
    ],
    "snore": [
      "T"
    ],
    "solarbeam": [
      "M"
    ],
    "strength": [
      "M"
    ],
    "substitute": [
      "M"
    ],
    "sunnyday": [
      "M"
    ],
    "swagger": [
      "M"
    ],
    "tackle": [
      "L:1"
    ],
    "takedown": [
      "L:20"
    ],
    "taunt": [
      "M"
    ],
    "thief": [
      "M"
    ],
    "toxic": [
      "M"
    ],
    "wildcharge": [
      "M"
    ],
    "willowisp": [
      "M"
    ],
    "workup": [
      "L:8"
    ],
    "yawn": [
      "E"
    ]
  }
}
