{
  "slug": "fakeout",
  "name": "Fake Out",
  "gen": 3,
  "type": "normal",
  "category": "physical",
  "basePower": 40,
  "accuracy": 100,
  "pp": 10,
  "target": "normal",
  "priority": 1,
  "pokemon": [
    "aipom",
    "ambipom",
    "blastoise",
    "buneary",
    "chimchar",
    "croagunk",
    "delcatty",
    "delibird",
    "dewgong",
    "glameow",
    "hariyama",
    "hitmonchan",
    "hitmonlee",
    "hitmontop",
    "infernape",
    "jynx",
    "kangaskhan",
    "kecleon",
    "lombre",
    "lopunny",
    "ludicolo",
    "makuhita",
    "medicham",
    "meditite",
    "meowth",
    "mimejr",
    "monferno",
    "mrmime",
    "nuzleaf",
    "persian",
    "pichu",
    "pikachu",
    "purugly",
    "raichu",
    "sableye",
    "seel",
    "shiftry",
    "skitty",
    "smoochum",
    "sneasel",
    "spinda",
    "squirtle",
    "toxicroak",
    "tyrogue",
    "wartortle",
    "weavile"
  ],
  "desc": "Has a 100% chance to make the target flinch. Fails unless it is the user's first turn on the field.",
  "shortDesc": "Hits first. First turn out only. 100% flinch chance."
}
