{
  "slug": "gust",
  "name": "Gust",
  "gen": 1,
  "type": "flying",
  "category": "special",
  "basePower": 40,
  "accuracy": 100,
  "pp": 35,
  "target": "any",
  "priority": 0,
  "pokemon": [
    "articuno",
    "beautifly",
    "butterfree",
    "combee",
    "crobat",
    "drifblim",
    "drifloon",
    "dustox",
    "farfetchd",
    "finneon",
    "flygon",
    "golbat",
    "hooh",
    "lugia",
    "lumineon",
    "masquerain",
    "mothim",
    "nincada",
    "ninjask",
    "pelipper",
    "pidgeot",
    "pidgeotto",
    "pidgey",
    "shedinja",
    "suicune",
    "trapinch",
    "tropius",
    "venomoth",
    "vespiquen",
    "vibrava",
    "wingull",
    "zubat"
  ],
  "desc": "Power doubles if the target is using Bounce or Fly.",
  "shortDesc": "Power doubles during Bounce and Fly."
}
