{
  "slug": "worryseed",
  "name": "Worry Seed",
  "gen": 4,
  "type": "grass",
  "category": "status",
  "basePower": 0,
  "accuracy": 100,
  "pp": 10,
  "target": "normal",
  "priority": 0,
  "pokemon": [
    "bulbasaur",
    "ivysaur",
    "venusaur",
    "vileplume",
    "victreebel",
    "chikorita",
    "bayleef",
    "meganium",
    "bellossom",
    "jumpluff",
    "treecko",
    "grovyle",
    "sceptile",
    "turtwig",
    "grotle",
    "torterra",
    "roserade",
    "exeggutor",
    "wormadam",
    "cherrim",
    "leafeon",
    "oddish",
    "gloom",
    "paras",
    "parasect",
    "psyduck",
    "golduck",
    "bellsprout",
    "weepinbell",
    "exeggcute",
    "tangela",
    "mew",
    "hoppip",
    "skiploom",
    "sunkern",
    "sunflora",
    "celebi",
    "seedot",
    "nuzleaf",
    "shiftry",
    "shroomish",
    "breloom",
    "roselia",
    "cacnea",
    "cacturne",
    "lileep",
    "cradily",
    "tropius",
    "budew",
    "cherubi",
    "cherrim-sunshine",
    "carnivine",
    "snover",
    "abomasnow",
    "tangrowth",
    "shaymin",
    "shaymin-sky"
  ],
  "desc": "Causes the target's Ability to become Insomnia. Fails if the target's Ability is Multitype or Truant, or if the target is holding a Griseous Orb.",
  "shortDesc": "The target's Ability becomes Insomnia."
}
