{
  "slug": "espeon",
  "name": "Espeon",
  "num": 196,
  "types": [
    "psychic"
  ],
  "gen": 2,
  "abilities": {
    "0": "synchronize"
  },
  "baseStats": {
    "hp": 65,
    "atk": 65,
    "def": 60,
    "spa": 130,
    "spd": 95,
    "spe": 110
  },
  "prevo": "eevee",
  "evoType": "levelFriendship",
  "evoCondition": "during the day",
  "weight": 26.5,
  "height": 0.9,
  "genderRatio": {
    "M": 0.875,
    "F": 0.125
  },
  "eggGroups": [
    "Field"
  ],
  "learnset": {
    "attract": [
      "4M",
      "4S0"
    ],
    "calmmind": [
      "4M"
    ],
    "captivate": [
      "4M"
    ],
    "confusion": [
      "4L15"
    ],
    "cut": [
      "4M"
    ],
    "dig": [
      "4M"
    ],
    "doubleteam": [
      "4M"
    ],
    "dreameater": [
      "4M"
    ],
    "endure": [
      "4M",
      "4E"
    ],
    "facade": [
      "4M"
    ],
    "flash": [
      "4M"
    ],
    "frustration": [
      "4M"
    ],
    "futuresight": [
      "4L43"
    ],
    "gigaimpact": [
      "4M"
    ],
    "grassknot": [
      "4M"
    ],
    "headbutt": [
      "4T"
    ],
    "healbell": [
      "4T"
    ],
    "helpinghand": [
      "4T",
      "4L1",
      "4S0"
    ],
    "hiddenpower": [
      "4M"
    ],
    "hyperbeam": [
      "4M"
    ],
    "irontail": [
      "4M",
      "4S1"
    ],
    "lastresort": [
      "4T",
      "4L50"
    ],
    "lightscreen": [
      "4M"
    ],
    "magiccoat": [
      "4T"
    ],
    "morningsun": [
      "4L71"
    ],
    "mudslap": [
      "4T"
    ],
    "naturalgift": [
      "4M"
    ],
    "powerswap": [
      "4L78"
    ],
    "protect": [
      "4M"
    ],
    "psybeam": [
      "4L36"
    ],
    "psychic": [
      "4M",
      "4L64"
    ],
    "psychup": [
      "4M",
      "4L57"
    ],
    "quickattack": [
      "4L22",
      "4S1"
    ],
    "raindance": [
      "4M"
    ],
    "reflect": [
      "4M"
    ],
    "rest": [
      "4M"
    ],
    "return": [
      "4M"
    ],
    "sandattack": [
      "4L8"
    ],
    "secretpower": [
      "4M"
    ],
    "shadowball": [
      "4M"
    ],
    "signalbeam": [
      "4T"
    ],
    "skillswap": [
      "4M"
    ],
    "sleeptalk": [
      "4M"
    ],
    "snore": [
      "4T"
    ],
    "substitute": [
      "4M"
    ],
    "sunnyday": [
      "4M"
    ],
    "swagger": [
      "4M"
    ],
    "swift": [
      "4T"
    ],
    "tackle": [
      "4L1"
    ],
    "tailwhip": [
      "4L1"
    ],
    "toxic": [
      "4M"
    ],
    "trick": [
      "4T"
    ],
    "trickroom": [
      "4M"
    ],
    "zenheadbutt": [
      "4T"
    ],
    "batonpass": [
      "4L36"
    ],
    "bite": [
      "4L29",
      "4S0"
    ],
    "charm": [
      "4E"
    ],
    "covet": [
      "4E",
      "4S0"
    ],
    "curse": [
      "4E"
    ],
    "detect": [
      "4E"
    ],
    "faketears": [
      "4E"
    ],
    "flail": [
      "4E",
      "4S1"
    ],
    "growl": [
      "4L15"
    ],
    "takedown": [
      "4L43"
    ],
    "tickle": [
      "4E"
    ],
    "trumpcard": [
      "4L57",
      "4S1"
    ],
    "wish": [
      "4E"
    ],
    "yawn": [
      "4E"
    ]
  }
}
