{
  "slug": "groudon",
  "name": "Groudon",
  "num": 383,
  "types": [
    "ground"
  ],
  "gen": 3,
  "abilities": {
    "0": "drought"
  },
  "baseStats": {
    "hp": 100,
    "atk": 150,
    "def": 140,
    "spa": 100,
    "spd": 90,
    "spe": 90
  },
  "weight": 950,
  "height": 3.5,
  "gender": "N",
  "eggGroups": [
    "Undiscovered"
  ],
  "isLegendary": true,
  "learnset": {
    "aerialace": [
      "4M"
    ],
    "ancientpower": [
      "4T",
      "4L15",
      "4S2"
    ],
    "block": [
      "4T"
    ],
    "brickbreak": [
      "4M"
    ],
    "bulkup": [
      "4M",
      "4L30"
    ],
    "cut": [
      "4M"
    ],
    "dig": [
      "4M"
    ],
    "doubleteam": [
      "4M"
    ],
    "dragonclaw": [
      "4M"
    ],
    "dragonpulse": [
      "4M"
    ],
    "earthpower": [
      "4T",
      "4L65"
    ],
    "earthquake": [
      "4M",
      "4L35",
      "4S2"
    ],
    "endure": [
      "4M"
    ],
    "eruption": [
      "4L50",
      "4S2"
    ],
    "facade": [
      "4M"
    ],
    "fireblast": [
      "4M",
      "4L45"
    ],
    "firepunch": [
      "4T"
    ],
    "fissure": [
      "4L60"
    ],
    "flamethrower": [
      "4M"
    ],
    "fling": [
      "4M"
    ],
    "focusblast": [
      "4M"
    ],
    "frustration": [
      "4M"
    ],
    "furycutter": [
      "4T"
    ],
    "gigaimpact": [
      "4M"
    ],
    "hammerarm": [
      "4L20"
    ],
    "headbutt": [
      "4T"
    ],
    "hiddenpower": [
      "4M"
    ],
    "hyperbeam": [
      "4M"
    ],
    "ironhead": [
      "4T"
    ],
    "irontail": [
      "4M"
    ],
    "lavaplume": [
      "4L15"
    ],
    "mudshot": [
      "4L1"
    ],
    "mudslap": [
      "4T"
    ],
    "naturalgift": [
      "4M"
    ],
    "overheat": [
      "4M"
    ],
    "protect": [
      "4M"
    ],
    "psychup": [
      "4M"
    ],
    "rest": [
      "4M",
      "4L30",
      "4S2"
    ],
    "return": [
      "4M"
    ],
    "roar": [
      "4M"
    ],
    "rockclimb": [
      "4M"
    ],
    "rockpolish": [
      "4M"
    ],
    "rockslide": [
      "4M"
    ],
    "rocksmash": [
      "4M"
    ],
    "rocktomb": [
      "4M"
    ],
    "rollout": [
      "4T"
    ],
    "safeguard": [
      "4M"
    ],
    "sandstorm": [
      "4M"
    ],
    "scaryface": [
      "4L5"
    ],
    "secretpower": [
      "4M"
    ],
    "shadowclaw": [
      "4M"
    ],
    "shockwave": [
      "4M"
    ],
    "slash": [
      "4L20"
    ],
    "sleeptalk": [
      "4M"
    ],
    "snore": [
      "4T"
    ],
    "solarbeam": [
      "4M",
      "4L65"
    ],
    "stealthrock": [
      "4M"
    ],
    "stoneedge": [
      "4M"
    ],
    "strength": [
      "4M"
    ],
    "substitute": [
      "4M"
    ],
    "sunnyday": [
      "4M"
    ],
    "swagger": [
      "4M"
    ],
    "swift": [
      "4T"
    ],
    "swordsdance": [
      "4M"
    ],
    "thunder": [
      "4M"
    ],
    "thunderbolt": [
      "4M"
    ],
    "thunderpunch": [
      "4T"
    ],
    "thunderwave": [
      "4M"
    ],
    "toxic": [
      "4M"
    ],
    "uproar": [
      "4T"
    ]
  }
}
