{
  "slug": "raticate",
  "name": "Raticate",
  "num": 20,
  "types": [
    "normal"
  ],
  "gen": 1,
  "abilities": {
    "0": "runaway",
    "1": "guts"
  },
  "baseStats": {
    "hp": 55,
    "atk": 81,
    "def": 60,
    "spa": 50,
    "spd": 70,
    "spe": 97
  },
  "prevo": "rattata",
  "evoLevel": 20,
  "weight": 18.5,
  "height": 0.7,
  "genderRatio": {
    "M": 0.5,
    "F": 0.5
  },
  "eggGroups": [
    "Field"
  ],
  "learnset": {
    "assurance": [
      "4L25"
    ],
    "attract": [
      "4M"
    ],
    "bite": [
      "4L10",
      "4E"
    ],
    "blizzard": [
      "4M"
    ],
    "captivate": [
      "4M"
    ],
    "chargebeam": [
      "4M"
    ],
    "counter": [
      "4E"
    ],
    "crunch": [
      "4L22"
    ],
    "cut": [
      "4M"
    ],
    "dig": [
      "4M"
    ],
    "doubleedge": [
      "4L31"
    ],
    "doubleteam": [
      "4M"
    ],
    "endeavor": [
      "4T",
      "4L34"
    ],
    "endure": [
      "4M"
    ],
    "facade": [
      "4M"
    ],
    "focusenergy": [
      "4L7"
    ],
    "frustration": [
      "4M"
    ],
    "gigaimpact": [
      "4M"
    ],
    "grassknot": [
      "4M"
    ],
    "headbutt": [
      "4T"
    ],
    "hiddenpower": [
      "4M"
    ],
    "hyperbeam": [
      "4M"
    ],
    "hyperfang": [
      "4L16"
    ],
    "icebeam": [
      "4M"
    ],
    "icywind": [
      "4T"
    ],
    "irontail": [
      "4M"
    ],
    "lastresort": [
      "4T",
      "4E"
    ],
    "mudslap": [
      "4T"
    ],
    "naturalgift": [
      "4M"
    ],
    "pluck": [
      "4M"
    ],
    "protect": [
      "4M"
    ],
    "pursuit": [
      "4L13"
    ],
    "quickattack": [
      "4L4"
    ],
    "raindance": [
      "4M"
    ],
    "rest": [
      "4M"
    ],
    "return": [
      "4M"
    ],
    "roar": [
      "4M"
    ],
    "rocksmash": [
      "4M"
    ],
    "scaryface": [
      "4L20"
    ],
    "secretpower": [
      "4M"
    ],
    "shadowball": [
      "4M"
    ],
    "shockwave": [
      "4M"
    ],
    "sleeptalk": [
      "4M"
    ],
    "snore": [
      "4T"
    ],
    "strength": [
      "4M"
    ],
    "substitute": [
      "4M"
    ],
    "suckerpunch": [
      "4T",
      "4L19"
    ],
    "sunnyday": [
      "4M"
    ],
    "superfang": [
      "4T",
      "4L28"
    ],
    "swagger": [
      "4M",
      "4E"
    ],
    "swift": [
      "4T"
    ],
    "swordsdance": [
      "4M",
      "4L1"
    ],
    "tackle": [
      "4L1"
    ],
    "tailwhip": [
      "4L1"
    ],
    "taunt": [
      "4M"
    ],
    "thief": [
      "4M"
    ],
    "thunder": [
      "4M"
    ],
    "thunderbolt": [
      "4M"
    ],
    "thunderwave": [
      "4M"
    ],
    "toxic": [
      "4M"
    ],
    "uturn": [
      "4M"
    ],
    "zenheadbutt": [
      "4T"
    ],
    "flamewheel": [
      "4E"
    ],
    "furyswipes": [
      "4E"
    ],
    "mefirst": [
      "4E"
    ],
    "reversal": [
      "4E"
    ],
    "screech": [
      "4E"
    ],
    "uproar": [
      "4E"
    ]
  }
}
