{
  "slug": "electrode",
  "name": "Electrode",
  "num": 101,
  "types": [
    "electric"
  ],
  "gen": 1,
  "abilities": {
    "0": "soundproof",
    "1": "static"
  },
  "baseStats": {
    "hp": 60,
    "atk": 50,
    "def": 70,
    "spa": 80,
    "spd": 80,
    "spe": 140
  },
  "prevo": "voltorb",
  "evoLevel": 30,
  "weight": 66.6,
  "height": 1.2,
  "gender": "N",
  "eggGroups": [
    "Mineral"
  ],
  "learnset": {
    "charge": [
      "L:1"
    ],
    "doubleteam": [
      "M"
    ],
    "endure": [
      "T"
    ],
    "explosion": [
      "T",
      "L:46"
    ],
    "facade": [
      "M"
    ],
    "flash": [
      "M"
    ],
    "frustration": [
      "M"
    ],
    "hiddenpower": [
      "M"
    ],
    "hyperbeam": [
      "M"
    ],
    "lightscreen": [
      "M",
      "L:37"
    ],
    "mimic": [
      "T"
    ],
    "mirrorcoat": [
      "L:49",
      "S:0"
    ],
    "protect": [
      "M"
    ],
    "raindance": [
      "M"
    ],
    "rest": [
      "M"
    ],
    "return": [
      "M"
    ],
    "rollout": [
      "T",
      "L:32"
    ],
    "screech": [
      "L:8"
    ],
    "secretpower": [
      "M"
    ],
    "selfdestruct": [
      "T",
      "L:27"
    ],
    "shockwave": [
      "M"
    ],
    "sleeptalk": [
      "T"
    ],
    "snore": [
      "T"
    ],
    "sonicboom": [
      "L:15"
    ],
    "spark": [
      "L:21",
      "S:0"
    ],
    "substitute": [
      "T"
    ],
    "swagger": [
      "T"
    ],
    "swift": [
      "T",
      "L:42",
      "S:0"
    ],
    "tackle": [
      "L:1"
    ],
    "taunt": [
      "M"
    ],
    "thief": [
      "M"
    ],
    "thunder": [
      "M"
    ],
    "thunderbolt": [
      "M"
    ],
    "thunderwave": [
      "T"
    ],
    "torment": [
      "M"
    ],
    "toxic": [
      "M"
    ],
    "refresh": [
      "S:0"
    ]
  }
}
