{
  "id": 737,
  "name": "throat-chop",
  "caption": "Throat Chop",
  "type": "dark",
  "category": "physical",
  "accuracy": 100,
  "basePower": 80,
  "pp": 15,
  "priority": 0,
  "target": "normal",
  "desc": "For 2 turns, the target cannot use sound-based moves.",
  "shortDesc": "For 2 turns, the target cannot use sound moves.",
  "pokemon": [
    "arrokuda",
    "barraskewda",
    "beartic",
    "bisharp",
    "corsola",
    "corsola-galar",
    "cramorant",
    "cramorant-gorging",
    "cramorant-gulping",
    "cursola",
    "drapion",
    "drednaw",
    "drednaw-gmax",
    "falinks",
    "farfetchd",
    "farfetchd-galar",
    "flygon",
    "gallade",
    "galvantula",
    "gigalith",
    "goldeen",
    "golisopod",
    "grimmsnarl",
    "grimmsnarl-gmax",
    "hawlucha",
    "heatmor",
    "hitmonchan",
    "hitmonlee",
    "hydreigon",
    "incineroar",
    "liepard",
    "linoone",
    "linoone-galar",
    "machamp",
    "machamp-gmax",
    "malamar",
    "maractus",
    "marshadow",
    "meowth",
    "meowth-alola",
    "meowth-galar",
    "meowth-gmax",
    "mew",
    "morgrem",
    "obstagoon",
    "pangoro",
    "perrserker",
    "persian",
    "persian-alola",
    "pincurchin",
    "qwilfish",
    "rapidash",
    "rapidash-galar",
    "sawk",
    "scrafty",
    "seaking",
    "shiftry",
    "sirfetchd",
    "skuntank",
    "sneasel",
    "stunky",
    "toxicroak",
    "toxtricity",
    "toxtricity-gmax",
    "toxtricity-low-key",
    "umbreon",
    "vibrava",
    "weavile",
    "zeraora"
  ]
}
