{
  "slug": "charmeleon",
  "name": "Charmeleon",
  "num": 5,
  "types": [
    "fire"
  ],
  "gen": 1,
  "abilities": {
    "0": "blaze",
    "H": "solarpower"
  },
  "baseStats": {
    "hp": 58,
    "atk": 64,
    "def": 58,
    "spa": 80,
    "spd": 65,
    "spe": 80
  },
  "prevo": "charmander",
  "evos": [
    "charizard"
  ],
  "evoLevel": 16,
  "weight": 19,
  "height": 1.1,
  "genderRatio": {
    "M": 0.875,
    "F": 0.125
  },
  "eggGroups": [
    "Monster",
    "Dragon"
  ],
  "learnset": {
    "aerialace": [
      "M"
    ],
    "aircutter": [
      "E@charmander"
    ],
    "ancientpower": [
      "E@charmander"
    ],
    "attract": [
      "M"
    ],
    "beatup": [
      "E@charmander"
    ],
    "bellydrum": [
      "E@charmander"
    ],
    "bite": [
      "E@charmander"
    ],
    "brickbreak": [
      "M"
    ],
    "confide": [
      "M"
    ],
    "counter": [
      "E@charmander"
    ],
    "crunch": [
      "E@charmander"
    ],
    "doubleteam": [
      "M"
    ],
    "dragonclaw": [
      "M"
    ],
    "dragondance": [
      "E@charmander"
    ],
    "dragonpulse": [
      "T",
      "E@charmander"
    ],
    "dragonrage": [
      "L:17"
    ],
    "dragonrush": [
      "E@charmander"
    ],
    "echoedvoice": [
      "M"
    ],
    "ember": [
      "L:1"
    ],
    "facade": [
      "M"
    ],
    "fireblast": [
      "M"
    ],
    "firefang": [
      "L:28"
    ],
    "firepledge": [
      "T"
    ],
    "firepunch": [
      "T"
    ],
    "firespin": [
      "L:50"
    ],
    "flameburst": [
      "L:32"
    ],
    "flamecharge": [
      "M"
    ],
    "flamethrower": [
      "M",
      "L:43"
    ],
    "flareblitz": [
      "E@charmander"
    ],
    "fling": [
      "M"
    ],
    "focuspunch": [
      "T",
      "E@charmander"
    ],
    "frustration": [
      "M"
    ],
    "growl": [
      "L:1"
    ],
    "heatwave": [
      "T"
    ],
    "hiddenpower": [
      "M"
    ],
    "inferno": [
      "L:54"
    ],
    "irontail": [
      "T"
    ],
    "metalclaw": [
      "E@charmander"
    ],
    "outrage": [
      "E@charmander"
    ],
    "overheat": [
      "M"
    ],
    "protect": [
      "M"
    ],
    "rest": [
      "M"
    ],
    "return": [
      "M"
    ],
    "rockslide": [
      "M"
    ],
    "rocktomb": [
      "M"
    ],
    "round": [
      "M"
    ],
    "scaryface": [
      "L:21"
    ],
    "scratch": [
      "L:1"
    ],
    "shadowclaw": [
      "M"
    ],
    "slash": [
      "L:39"
    ],
    "sleeptalk": [
      "M"
    ],
    "smokescreen": [
      "L:10"
    ],
    "snore": [
      "T"
    ],
    "substitute": [
      "M"
    ],
    "sunnyday": [
      "M"
    ],
    "swagger": [
      "M"
    ],
    "swordsdance": [
      "M"
    ],
    "thunderpunch": [
      "T"
    ],
    "toxic": [
      "M"
    ],
    "willowisp": [
      "M"
    ],
    "workup": [
      "M"
    ]
  }
}
