{
  "slug": "drowzee",
  "name": "Drowzee",
  "num": 96,
  "types": [
    "psychic"
  ],
  "gen": 1,
  "abilities": {
    "0": "insomnia",
    "1": "forewarn",
    "H": "innerfocus"
  },
  "baseStats": {
    "hp": 60,
    "atk": 48,
    "def": 45,
    "spa": 43,
    "spd": 90,
    "spe": 42
  },
  "evos": [
    "hypno"
  ],
  "weight": 32.4,
  "height": 1,
  "genderRatio": {
    "M": 0.5,
    "F": 0.5
  },
  "eggGroups": [
    "Human-Like"
  ],
  "canHatch": true,
  "learnset": {
    "allyswitch": [
      "T"
    ],
    "assist": [
      "E"
    ],
    "attract": [
      "M"
    ],
    "barrier": [
      "E"
    ],
    "brickbreak": [
      "M"
    ],
    "calmmind": [
      "M"
    ],
    "confide": [
      "M"
    ],
    "confusion": [
      "L:9"
    ],
    "dazzlinggleam": [
      "M"
    ],
    "disable": [
      "L:5"
    ],
    "doubleteam": [
      "M"
    ],
    "drainpunch": [
      "T"
    ],
    "dreameater": [
      "M"
    ],
    "facade": [
      "M"
    ],
    "firepunch": [
      "T",
      "E"
    ],
    "flatter": [
      "E"
    ],
    "fling": [
      "M"
    ],
    "focuspunch": [
      "T"
    ],
    "foulplay": [
      "T"
    ],
    "frustration": [
      "M"
    ],
    "futuresight": [
      "L:61"
    ],
    "grassknot": [
      "M"
    ],
    "guardswap": [
      "E"
    ],
    "headbutt": [
      "L:13"
    ],
    "hiddenpower": [
      "M"
    ],
    "hypnosis": [
      "L:1"
    ],
    "icepunch": [
      "T",
      "E"
    ],
    "lightscreen": [
      "M"
    ],
    "lowkick": [
      "T"
    ],
    "lowsweep": [
      "M"
    ],
    "magiccoat": [
      "T"
    ],
    "magicroom": [
      "T"
    ],
    "meditate": [
      "L:21"
    ],
    "nastyplot": [
      "L:53",
      "E"
    ],
    "poisongas": [
      "L:17"
    ],
    "pound": [
      "L:1"
    ],
    "powersplit": [
      "E"
    ],
    "protect": [
      "M"
    ],
    "psybeam": [
      "L:25"
    ],
    "psychic": [
      "M",
      "L:49"
    ],
    "psychicterrain": [
      "E"
    ],
    "psychocut": [
      "E"
    ],
    "psychup": [
      "M",
      "L:33"
    ],
    "psyshock": [
      "M",
      "L:57"
    ],
    "raindance": [
      "M"
    ],
    "recycle": [
      "T"
    ],
    "reflect": [
      "M"
    ],
    "rest": [
      "M"
    ],
    "return": [
      "M"
    ],
    "roleplay": [
      "T",
      "E"
    ],
    "round": [
      "M"
    ],
    "safeguard": [
      "M"
    ],
    "secretpower": [
      "E"
    ],
    "shadowball": [
      "M"
    ],
    "signalbeam": [
      "T"
    ],
    "skillswap": [
      "T",
      "E"
    ],
    "sleeptalk": [
      "M"
    ],
    "snatch": [
      "T"
    ],
    "snore": [
      "T"
    ],
    "substitute": [
      "M"
    ],
    "sunnyday": [
      "M"
    ],
    "swagger": [
      "M",
      "L:45"
    ],
    "synchronoise": [
      "L:37"
    ],
    "taunt": [
      "M"
    ],
    "telekinesis": [
      "T"
    ],
    "thief": [
      "M"
    ],
    "thunderpunch": [
      "T",
      "E"
    ],
    "thunderwave": [
      "M"
    ],
    "torment": [
      "M"
    ],
    "toxic": [
      "M"
    ],
    "trick": [
      "T"
    ],
    "trickroom": [
      "M"
    ],
    "wakeupslap": [
      "L:29"
    ],
    "zenheadbutt": [
      "T",
      "L:41"
    ]
  }
}
