{
  "slug": "pikachu",
  "name": "Pikachu",
  "num": 25,
  "types": [
    "electric"
  ],
  "gen": 1,
  "abilities": {
    "0": "static",
    "H": "lightningrod"
  },
  "baseStats": {
    "hp": 35,
    "atk": 55,
    "def": 40,
    "spa": 50,
    "spd": 50,
    "spe": 90
  },
  "prevo": "pichu",
  "evos": [
    "raichu"
  ],
  "evoType": "levelFriendship",
  "formes": [
    "pikachu-cosplay",
    "pikachu-rock-star",
    "pikachu-belle",
    "pikachu-pop-star",
    "pikachu-phd",
    "pikachu-libre"
  ],
  "weight": 6,
  "height": 0.4,
  "genderRatio": {
    "M": 0.5,
    "F": 0.5
  },
  "eggGroups": [
    "Field",
    "Fairy"
  ],
  "learnset": {
    "agility": [
      "L:37"
    ],
    "attract": [
      "M"
    ],
    "bestow": [
      "E"
    ],
    "brickbreak": [
      "M"
    ],
    "celebrate": [
      "S"
    ],
    "chargebeam": [
      "M"
    ],
    "charm": [
      "L:1"
    ],
    "confide": [
      "M"
    ],
    "covet": [
      "T"
    ],
    "dig": [
      "M"
    ],
    "discharge": [
      "L:34"
    ],
    "doubleteam": [
      "M",
      "L:21"
    ],
    "echoedvoice": [
      "M"
    ],
    "electroball": [
      "L:13"
    ],
    "electroweb": [
      "T"
    ],
    "encore": [
      "E"
    ],
    "endeavor": [
      "S"
    ],
    "endure": [
      "E"
    ],
    "facade": [
      "M"
    ],
    "fakeout": [
      "E"
    ],
    "feint": [
      "L:21"
    ],
    "flash": [
      "M"
    ],
    "fling": [
      "M"
    ],
    "fly": [
      "S"
    ],
    "focuspunch": [
      "T"
    ],
    "frustration": [
      "M"
    ],
    "grassknot": [
      "M"
    ],
    "growl": [
      "L:5"
    ],
    "happyhour": [
      "S"
    ],
    "heartstamp": [
      "S"
    ],
    "helpinghand": [
      "T"
    ],
    "hiddenpower": [
      "M"
    ],
    "holdhands": [
      "S"
    ],
    "irontail": [
      "T"
    ],
    "knockoff": [
      "T"
    ],
    "lightscreen": [
      "M",
      "L:45"
    ],
    "magnetrise": [
      "T"
    ],
    "megakick": [
      "S"
    ],
    "nuzzle": [
      "L:23"
    ],
    "playnice": [
      "L:7"
    ],
    "present": [
      "E"
    ],
    "protect": [
      "M"
    ],
    "quickattack": [
      "L:10"
    ],
    "raindance": [
      "M"
    ],
    "rest": [
      "M"
    ],
    "return": [
      "M"
    ],
    "rocksmash": [
      "M"
    ],
    "round": [
      "M"
    ],
    "secretpower": [
      "M"
    ],
    "shockwave": [
      "T"
    ],
    "signalbeam": [
      "T"
    ],
    "slam": [
      "L:26"
    ],
    "sleeptalk": [
      "M"
    ],
    "snore": [
      "T"
    ],
    "spark": [
      "L:26"
    ],
    "strength": [
      "M"
    ],
    "substitute": [
      "M"
    ],
    "surf": [
      "S"
    ],
    "swagger": [
      "M"
    ],
    "sweetkiss": [
      "L:10"
    ],
    "tailwhip": [
      "L:1"
    ],
    "teeterdance": [
      "S"
    ],
    "thunder": [
      "M",
      "L:50"
    ],
    "thunderbolt": [
      "M",
      "L:29"
    ],
    "thunderpunch": [
      "T",
      "E"
    ],
    "thundershock": [
      "L:1"
    ],
    "thunderwave": [
      "M",
      "L:13"
    ],
    "toxic": [
      "M"
    ],
    "voltswitch": [
      "M"
    ],
    "volttackle": [
      "E"
    ],
    "wildcharge": [
      "M",
      "L:50"
    ],
    "bide": [
      "E"
    ],
    "charge": [
      "E"
    ],
    "disarmingvoice": [
      "E"
    ],
    "doubleslap": [
      "E"
    ],
    "flail": [
      "E"
    ],
    "luckychant": [
      "E"
    ],
    "nastyplot": [
      "L:13"
    ],
    "reversal": [
      "E"
    ],
    "tickle": [
      "E"
    ],
    "uproar": [
      "T"
    ],
    "wish": [
      "E"
    ]
  }
}
