{
  "slug": "raichu",
  "name": "Raichu",
  "num": 26,
  "types": [
    "electric"
  ],
  "gen": 1,
  "abilities": {
    "0": "static",
    "H": "lightningrod"
  },
  "baseStats": {
    "hp": 60,
    "atk": 90,
    "def": 55,
    "spa": 90,
    "spd": 80,
    "spe": 110
  },
  "prevo": "pikachu",
  "evoType": "useItem",
  "evoItem": "Thunder Stone",
  "weight": 30,
  "height": 0.8,
  "genderRatio": {
    "M": 0.5,
    "F": 0.5
  },
  "eggGroups": [
    "Field",
    "Fairy"
  ],
  "learnset": {
    "attract": [
      "6M",
      "5M",
      "4M",
      "3M"
    ],
    "bodyslam": [
      "3T"
    ],
    "brickbreak": [
      "6M",
      "5M",
      "5S26",
      "4M",
      "3M"
    ],
    "captivate": [
      "4M"
    ],
    "chargebeam": [
      "6M",
      "5M",
      "4M"
    ],
    "confide": [
      "6M"
    ],
    "counter": [
      "3T"
    ],
    "covet": [
      "6T",
      "5T"
    ],
    "defensecurl": [
      "3T"
    ],
    "dig": [
      "6M",
      "5M",
      "4M",
      "3M"
    ],
    "doubleedge": [
      "3T"
    ],
    "doubleteam": [
      "6M",
      "5M",
      "4M",
      "3M"
    ],
    "dynamicpunch": [
      "3T"
    ],
    "echoedvoice": [
      "6M",
      "5M"
    ],
    "electroweb": [
      "6T"
    ],
    "endure": [
      "6E",
      "5E",
      "4M",
      "4S5",
      "3T"
    ],
    "facade": [
      "6M",
      "5M",
      "4M",
      "3M"
    ],
    "flash": [
      "6M",
      "5M",
      "4M",
      "3M"
    ],
    "fling": [
      "6M",
      "5M",
      "4M"
    ],
    "focusblast": [
      "6M",
      "5M",
      "4M"
    ],
    "focuspunch": [
      "6T",
      "4M",
      "3M"
    ],
    "frustration": [
      "6M",
      "5M",
      "4M",
      "3M"
    ],
    "gigaimpact": [
      "6M",
      "5M",
      "4M"
    ],
    "grassknot": [
      "6M",
      "5M",
      "4M",
      "4S4"
    ],
    "headbutt": [
      "4T"
    ],
    "helpinghand": [
      "6T",
      "5T",
      "4T"
    ],
    "hiddenpower": [
      "6M",
      "5M",
      "4M",
      "3M"
    ],
    "hyperbeam": [
      "6M",
      "5M",
      "4M",
      "3M"
    ],
    "irontail": [
      "6T",
      "5T",
      "4M",
      "3M"
    ],
    "knockoff": [
      "6T",
      "5T",
      "4T"
    ],
    "lightscreen": [
      "6M",
      "5M",
      "4M",
      "3M"
    ],
    "magnetrise": [
      "6T",
      "5T",
      "4T"
    ],
    "megakick": [
      "3T"
    ],
    "megapunch": [
      "3T"
    ],
    "mimic": [
      "3T"
    ],
    "mudslap": [
      "4T",
      "3T"
    ],
    "naturalgift": [
      "4M"
    ],
    "protect": [
      "6M",
      "5M",
      "4M",
      "3M"
    ],
    "quickattack": [
      "6L10",
      "6S31",
      "6S32",
      "6S33",
      "6S34",
      "6S37",
      "5L13",
      "5S24",
      "5S25",
      "5S29",
      "5S30",
      "4L13",
      "4S11",
      "4S12",
      "4S15",
      "4S17",
      "4S18",
      "4S20",
      "4S21",
      "4S22",
      "3L11"
    ],
    "raindance": [
      "6M",
      "5M",
      "4M",
      "3M"
    ],
    "rest": [
      "6M",
      "5M",
      "4M",
      "3M"
    ],
    "return": [
      "6M",
      "5M",
      "4M",
      "4S4",
      "3M"
    ],
    "rocksmash": [
      "6M",
      "5M",
      "4M",
      "3M"
    ],
    "rollout": [
      "4T",
      "3T"
    ],
    "round": [
      "6M",
      "5M"
    ],
    "secretpower": [
      "6M",
      "4M",
      "3M"
    ],
    "seismictoss": [
      "3T"
    ],
    "shockwave": [
      "6T",
      "4M",
      "3M"
    ],
    "signalbeam": [
      "6T",
      "5T",
      "4T"
    ],
    "sleeptalk": [
      "6M",
      "5T",
      "4M",
      "3T"
    ],
    "snore": [
      "6T",
      "5T",
      "4T",
      "3T"
    ],
    "strength": [
      "6M",
      "5M",
      "4M",
      "3M"
    ],
    "substitute": [
      "6M",
      "5M",
      "4M",
      "3T"
    ],
    "swagger": [
      "6M",
      "5M",
      "4M",
      "3T"
    ],
    "swift": [
      "4T",
      "3T"
    ],
    "tailwhip": [
      "6L5",
      "5L5",
      "4L5",
      "3L6"
    ],
    "thief": [
      "6M",
      "5M",
      "4M",
      "3M"
    ],
    "thunder": [
      "6M",
      "5M",
      "4M",
      "3M"
    ],
    "thunderbolt": [
      "6M",
      "5M",
      "4M",
      "4S4",
      "3M"
    ],
    "thunderpunch": [
      "6T",
      "6E",
      "5E",
      "4E"
    ],
    "thundershock": [
      "6L1",
      "5L1",
      "4L1",
      "3L1",
      "3S0",
      "3S1",
      "3S2",
      "3S3"
    ],
    "thunderwave": [
      "6M",
      "6L13",
      "5M",
      "5L10",
      "4M",
      "4L10",
      "3T",
      "3L8"
    ],
    "toxic": [
      "6M",
      "5M",
      "4M",
      "3M"
    ],
    "voltswitch": [
      "6M",
      "5M"
    ],
    "wildcharge": [
      "6M",
      "5M"
    ],
    "agility": [
      "6L37",
      "6S41",
      "5L37",
      "4L34",
      "3L33",
      "3S0",
      "3S8"
    ],
    "bestow": [
      "6E",
      "5E"
    ],
    "celebrate": [
      "6S31",
      "6S41"
    ],
    "charm": [
      "6L1",
      "5L1",
      "4L1",
      "3L1",
      "3S0",
      "3S1",
      "3S2",
      "3S3"
    ],
    "discharge": [
      "6L34",
      "5L42",
      "4L37"
    ],
    "electroball": [
      "6L13",
      "6S32",
      "6S37",
      "5L18",
      "5S23",
      "5S24",
      "5S30"
    ],
    "encore": [
      "6E",
      "5E",
      "4E",
      "3E"
    ],
    "endeavor": [
      "4S5"
    ],
    "extremespeed": [
      "5S26"
    ],
    "fakeout": [
      "6E",
      "5E",
      "4E"
    ],
    "feint": [
      "6L21",
      "5L34",
      "5S29",
      "4L29"
    ],
    "fly": [
      "6S41",
      "5S24",
      "5S27",
      "3S2",
      "3S4",
      "3S6"
    ],
    "growl": [
      "6L5",
      "6S31",
      "5L1",
      "4L1",
      "3L1",
      "3S1",
      "3S2",
      "3S3",
      "3S4",
      "3S5",
      "3S10"
    ],
    "happyhour": [
      "6S40"
    ],
    "heartstamp": [
      "6S34"
    ],
    "holdhands": [
      "6S33",
      "6S34",
      "6S35",
      "6S40",
      "6S42"
    ],
    "lastresort": [
      "4S18"
    ],
    "nuzzle": [
      "6L23",
      "6S36",
      "6S38"
    ],
    "playnice": [
      "6L7",
      "6S31",
      "6S35",
      "6S36",
      "6S38",
      "6S40",
      "6S42"
    ],
    "present": [
      "6E",
      "5E",
      "4E",
      "3E"
    ],
    "sing": [
      "5S23"
    ],
    "slam": [
      "6L26",
      "5L26",
      "4L21",
      "3L20"
    ],
    "spark": [
      "6L26"
    ],
    "surf": [
      "6S33",
      "6S41",
      "4S9",
      "4S11",
      "4S14",
      "4S16",
      "3S3",
      "3S5",
      "3S7"
    ],
    "sweetkiss": [
      "6L10",
      "5L13",
      "4L13",
      "3L11"
    ],
    "teeterdance": [
      "3S2"
    ],
    "volttackle": [
      "6E",
      "5E",
      "4E",
      "4S4",
      "4S5",
      "3E"
    ],
    "yawn": [
      "4S19"
    ],
    "bide": [
      "6E",
      "5E",
      "4E",
      "3E"
    ],
    "charge": [
      "6E",
      "5E",
      "4E",
      "4S5",
      "3E"
    ],
    "disarmingvoice": [
      "6E"
    ],
    "doubleslap": [
      "6E",
      "5E",
      "4E",
      "3E"
    ],
    "flail": [
      "6E",
      "5E",
      "4E"
    ],
    "followme": [
      "3S3"
    ],
    "luckychant": [
      "6E",
      "5E"
    ],
    "nastyplot": [
      "6L13",
      "5L18",
      "4L18"
    ],
    "reversal": [
      "6E",
      "5E",
      "4E",
      "3E"
    ],
    "tickle": [
      "6E",
      "5E",
      "4E"
    ],
    "uproar": [
      "6T",
      "5T",
      "4T"
    ],
    "wish": [
      "6E",
      "5E",
      "4E",
      "3E",
      "3S1"
    ]
  }
}
