{
  "slug": "venusaur-mega",
  "name": "Mega Venusaur",
  "num": 3,
  "types": [
    "grass",
    "poison"
  ],
  "gen": 6,
  "abilities": {
    "0": "thickfat"
  },
  "baseStats": {
    "hp": 80,
    "atk": 100,
    "def": 123,
    "spa": 122,
    "spd": 120,
    "spe": 80
  },
  "baseSpecies": "venusaur",
  "formTriggerItem": "venusaurite",
  "isBattleOnly": true,
  "isMega": true,
  "weight": 155.5,
  "height": 2.4,
  "genderRatio": {
    "M": 0.875,
    "F": 0.125
  },
  "eggGroups": [
    "Monster",
    "Grass"
  ],
  "canHatch": true
}
