{
  "slug": "walrein",
  "name": "Walrein",
  "num": 365,
  "types": [
    "ice",
    "water"
  ],
  "gen": 3,
  "abilities": {
    "0": "thickfat",
    "1": "icebody",
    "H": "oblivious"
  },
  "baseStats": {
    "hp": 110,
    "atk": 80,
    "def": 90,
    "spa": 95,
    "spd": 90,
    "spe": 65
  },
  "prevo": "sealeo",
  "evoLevel": 44,
  "weight": 150.6,
  "height": 1.4,
  "genderRatio": {
    "M": 0.5,
    "F": 0.5
  },
  "eggGroups": [
    "Water 1",
    "Field"
  ],
  "learnset": {
    "aquaring": [
      "E"
    ],
    "aquatail": [
      "T"
    ],
    "attract": [
      "M"
    ],
    "aurorabeam": [
      "L:19"
    ],
    "bellydrum": [
      "E"
    ],
    "blizzard": [
      "M",
      "L:49"
    ],
    "block": [
      "T"
    ],
    "bodyslam": [
      "L:19"
    ],
    "brine": [
      "L:19"
    ],
    "bulldoze": [
      "M"
    ],
    "confide": [
      "M"
    ],
    "crunch": [
      "L:1"
    ],
    "curse": [
      "E"
    ],
    "defensecurl": [
      "L:1"
    ],
    "dive": [
      "M"
    ],
    "doubleteam": [
      "M"
    ],
    "earthquake": [
      "M"
    ],
    "echoedvoice": [
      "M"
    ],
    "encore": [
      "L:1"
    ],
    "facade": [
      "M"
    ],
    "fissure": [
      "E"
    ],
    "frostbreath": [
      "M"
    ],
    "frustration": [
      "M"
    ],
    "gigaimpact": [
      "M"
    ],
    "growl": [
      "L:1"
    ],
    "hail": [
      "M",
      "L:31"
    ],
    "hiddenpower": [
      "M"
    ],
    "hyperbeam": [
      "M"
    ],
    "iceball": [
      "L:13"
    ],
    "icebeam": [
      "M"
    ],
    "icefang": [
      "L:44"
    ],
    "icywind": [
      "T"
    ],
    "ironhead": [
      "T"
    ],
    "irontail": [
      "T"
    ],
    "powdersnow": [
      "L:1"
    ],
    "protect": [
      "M"
    ],
    "raindance": [
      "M"
    ],
    "rest": [
      "M",
      "L:31"
    ],
    "return": [
      "M"
    ],
    "roar": [
      "M"
    ],
    "rockslide": [
      "M"
    ],
    "rocksmash": [
      "M"
    ],
    "rocktomb": [
      "M"
    ],
    "rollout": [
      "L:7",
      "E"
    ],
    "round": [
      "M"
    ],
    "secretpower": [
      "M"
    ],
    "sheercold": [
      "L:60"
    ],
    "signalbeam": [
      "T",
      "E"
    ],
    "sleeptalk": [
      "M",
      "E"
    ],
    "snore": [
      "T",
      "L:31"
    ],
    "spitup": [
      "E"
    ],
    "stockpile": [
      "E"
    ],
    "strength": [
      "M"
    ],
    "substitute": [
      "M"
    ],
    "superfang": [
      "T"
    ],
    "surf": [
      "M"
    ],
    "swagger": [
      "M",
      "L:32"
    ],
    "swallow": [
      "E"
    ],
    "toxic": [
      "M"
    ],
    "waterfall": [
      "M"
    ],
    "watergun": [
      "L:1"
    ],
    "waterpulse": [
      "T",
      "E"
    ],
    "watersport": [
      "E"
    ],
    "yawn": [
      "E"
    ]
  }
}
