{
  "slug": "kommoo",
  "name": "Kommo-o",
  "num": 784,
  "types": [
    "dragon",
    "fighting"
  ],
  "gen": 7,
  "abilities": {
    "0": "bulletproof",
    "1": "soundproof",
    "H": "overcoat"
  },
  "baseStats": {
    "hp": 75,
    "atk": 110,
    "def": 125,
    "spa": 100,
    "spd": 105,
    "spe": 85
  },
  "prevo": "hakamoo",
  "evoLevel": 45,
  "weight": 78.2,
  "height": 1.6,
  "genderRatio": {
    "M": 0.5,
    "F": 0.5
  },
  "eggGroups": [
    "Dragon"
  ],
  "learnset": {
    "attract": [
      "8M"
    ],
    "aurasphere": [
      "8M"
    ],
    "autotomize": [
      "8L1"
    ],
    "bellydrum": [
      "8L1"
    ],
    "bodypress": [
      "8M"
    ],
    "boomburst": [
      "8L76"
    ],
    "breakingswipe": [
      "8M"
    ],
    "brickbreak": [
      "8M"
    ],
    "brutalswing": [
      "8M"
    ],
    "bulkup": [
      "8M"
    ],
    "bulldoze": [
      "8M"
    ],
    "clangingscales": [
      "8L0"
    ],
    "clangoroussoul": [
      "8L68"
    ],
    "closecombat": [
      "8M",
      "8L56"
    ],
    "coaching": [
      "8T"
    ],
    "dracometeor": [
      "8T"
    ],
    "dragonclaw": [
      "8M",
      "8L32"
    ],
    "dragondance": [
      "8M",
      "8L40"
    ],
    "dragonpulse": [
      "8M"
    ],
    "dragontail": [
      "8L8"
    ],
    "drainpunch": [
      "8M"
    ],
    "earthquake": [
      "8M"
    ],
    "endure": [
      "8M"
    ],
    "facade": [
      "8M"
    ],
    "falseswipe": [
      "8M"
    ],
    "firepunch": [
      "8M"
    ],
    "flamethrower": [
      "8M"
    ],
    "flashcannon": [
      "8M"
    ],
    "fling": [
      "8M"
    ],
    "focusblast": [
      "8M"
    ],
    "focuspunch": [
      "8E"
    ],
    "gigaimpact": [
      "8M"
    ],
    "headbutt": [
      "8L16"
    ],
    "hyperbeam": [
      "8M"
    ],
    "hypervoice": [
      "8M"
    ],
    "icepunch": [
      "8M"
    ],
    "irondefense": [
      "8M",
      "8L28"
    ],
    "ironhead": [
      "8M"
    ],
    "irontail": [
      "8M"
    ],
    "leer": [
      "8L1"
    ],
    "lowkick": [
      "8M"
    ],
    "megakick": [
      "8M"
    ],
    "megapunch": [
      "8M"
    ],
    "nobleroar": [
      "8L36"
    ],
    "outrage": [
      "8M",
      "8L44"
    ],
    "payback": [
      "8M"
    ],
    "poisonjab": [
      "8M"
    ],
    "protect": [
      "8M",
      "8L4"
    ],
    "rest": [
      "8M"
    ],
    "revenge": [
      "8M"
    ],
    "reversal": [
      "8M"
    ],
    "rockslide": [
      "8M"
    ],
    "rocktomb": [
      "8M"
    ],
    "round": [
      "8M"
    ],
    "safeguard": [
      "8M"
    ],
    "sandstorm": [
      "8M"
    ],
    "scaleshot": [
      "8T"
    ],
    "scaryface": [
      "8M",
      "8L12"
    ],
    "screech": [
      "8M",
      "8L24"
    ],
    "shadowclaw": [
      "8M"
    ],
    "sleeptalk": [
      "8M"
    ],
    "snore": [
      "8M"
    ],
    "stealthrock": [
      "8M"
    ],
    "stompingtantrum": [
      "8M"
    ],
    "substitute": [
      "8M"
    ],
    "superpower": [
      "8M"
    ],
    "swordsdance": [
      "8M"
    ],
    "tackle": [
      "8L1"
    ],
    "taunt": [
      "8M"
    ],
    "thunderpunch": [
      "8M"
    ],
    "uproar": [
      "8M"
    ],
    "workup": [
      "8M",
      "8L20"
    ],
    "xscissor": [
      "8M"
    ],
    "counter": [
      "8E"
    ],
    "dragonbreath": [
      "8E"
    ]
  }
}
