{
  "slug": "bugbite",
  "name": "Bug Bite",
  "gen": 4,
  "type": "bug",
  "category": "physical",
  "basePower": 60,
  "accuracy": 100,
  "pp": 20,
  "target": "normal",
  "priority": 0,
  "pokemon": [
    "ariados",
    "charjabug",
    "combee",
    "cutiefly",
    "dipplin",
    "fomantis",
    "forretress",
    "frosmoth",
    "grubbin",
    "heracross",
    "illumise",
    "kleavor",
    "kricketot",
    "kricketune",
    "larvesta",
    "leavanny",
    "lokix",
    "lurantis",
    "masquerain",
    "mew",
    "nymble",
    "pineco",
    "rabsca",
    "rellor",
    "ribombee",
    "scatterbug",
    "scizor",
    "scyther",
    "sewaddle",
    "slitherwing",
    "snom",
    "spewpa",
    "spidops",
    "spinarak",
    "surskit",
    "swadloon",
    "tarountula",
    "venomoth",
    "venonat",
    "vespiquen",
    "victreebel",
    "vikavolt",
    "vivillon",
    "vivillon-fancy",
    "volbeat",
    "volcarona",
    "weepinbell",
    "yanma",
    "yanmega"
  ],
  "desc": "If this move is successful and the user has not fainted, it steals the target's held Berry if it is holding one and eats it immediately, gaining its effects even if the user's item is being ignored. Items lost to this move cannot be regained with Recycle or the Harvest Ability.",
  "shortDesc": "User steals and eats the target's Berry.",
  "flavorText": {
    "sv": "The user attacks by biting the target. If the target is holding a Berry, the user eats it and gains its effect."
  }
}
