{
  "slug": "pound",
  "name": "Pound",
  "gen": 1,
  "type": "normal",
  "category": "physical",
  "basePower": 40,
  "accuracy": 100,
  "pp": 35,
  "target": "normal",
  "priority": 0,
  "pokemon": [
    "alomomola",
    "blissey",
    "brionne",
    "calyrex",
    "calyrex-ice",
    "calyrex-shadow",
    "chansey",
    "cinccino",
    "clefable",
    "clefairy",
    "cleffa",
    "conkeldurr",
    "drizzile",
    "drowzee",
    "empoleon",
    "finneon",
    "froakie",
    "frogadier",
    "golett",
    "golurk",
    "gothita",
    "gothitelle",
    "gothorita",
    "greninja",
    "greninja-bond",
    "grimer",
    "grimer-alola",
    "grovyle",
    "gulpin",
    "gurdurr",
    "happiny",
    "hypno",
    "igglybuff",
    "inteleon",
    "jigglypuff",
    "lumineon",
    "maushold",
    "maushold-four",
    "mew",
    "mienfoo",
    "mienshao",
    "minccino",
    "muk",
    "muk-alola",
    "oricorio",
    "oricorio-pau",
    "oricorio-pompom",
    "oricorio-sensu",
    "piplup",
    "politoed",
    "poliwag",
    "poliwhirl",
    "poliwrath",
    "popplio",
    "primarina",
    "prinplup",
    "quaquaval",
    "quaxly",
    "quaxwell",
    "regigigas",
    "salazzle",
    "sceptile",
    "screamtail",
    "sobble",
    "sunflora",
    "swalot",
    "tandemaus",
    "timburr",
    "treecko",
    "wigglytuff"
  ],
  "desc": "No additional effect.",
  "shortDesc": "No additional effect.",
  "flavorText": {
    "sv": "The target is physically pounded with a long tail, a foreleg, or the like."
  }
}
