{
  "slug": "assurance",
  "name": "Assurance",
  "gen": 4,
  "type": "dark",
  "category": "physical",
  "basePower": 60,
  "accuracy": 100,
  "pp": 10,
  "target": "normal",
  "priority": 0,
  "pokemon": [
    "absol",
    "aerodactyl",
    "archen",
    "archeops",
    "arrokuda",
    "axew",
    "azelf",
    "barbaracle",
    "barraskewda",
    "basculin",
    "basculin-blue-striped",
    "beartic",
    "beedrill",
    "binacle",
    "bisharp",
    "blaziken",
    "bouffalant",
    "braviary",
    "buneary",
    "cacnea",
    "cacturne",
    "calyrex-ice",
    "calyrex-shadow",
    "carvanha",
    "chewtle",
    "cinderace",
    "combusken",
    "corviknight",
    "corvisquire",
    "cramorant",
    "cranidos",
    "croagunk",
    "crobat",
    "cubchoo",
    "deino",
    "delibird",
    "dhelmise",
    "diglett",
    "diglett-alola",
    "dodrio",
    "doduo",
    "donphan",
    "dragapult",
    "drakloak",
    "drapion",
    "drednaw",
    "dugtrio",
    "dugtrio-alola",
    "eternatus",
    "eternatus-eternamax",
    "falinks",
    "farfetchd-galar",
    "fearow",
    "ferroseed",
    "ferrothorn",
    "fraxure",
    "genesect",
    "genesect-burn",
    "genesect-chill",
    "genesect-douse",
    "genesect-shock",
    "girafarig",
    "glameow",
    "glastrier",
    "golbat",
    "golisopod",
    "goodra",
    "greedent",
    "grimmsnarl",
    "grookey",
    "grovyle",
    "hawlucha",
    "haxorus",
    "heracross",
    "honchkrow",
    "hydreigon",
    "impidimp",
    "incineroar",
    "kangaskhan",
    "klang",
    "kleavor",
    "klink",
    "klinklang",
    "koffing",
    "krokorok",
    "krookodile",
    "larvitar",
    "liepard",
    "linoone-galar",
    "lopunny",
    "lycanroc",
    "machamp",
    "mandibuzz",
    "mankey",
    "mantine",
    "maractus",
    "marshadow",
    "mawile",
    "meowth",
    "meowth-alola",
    "meowth-galar",
    "mew",
    "mienshao",
    "mightyena",
    "moltres-galar",
    "morgrem",
    "morpeko",
    "murkrow",
    "naganadel",
    "nickit",
    "nuzleaf",
    "obstagoon",
    "octillery",
    "passimian",
    "pawniard",
    "perrserker",
    "persian",
    "persian-alola",
    "pheromosa",
    "pincurchin",
    "poochyena",
    "primeape",
    "pupitar",
    "purrloin",
    "purugly",
    "qwilfish",
    "raboot",
    "rampardos",
    "raticate",
    "rattata",
    "regieleki",
    "remoraid",
    "rillaboom",
    "rookidee",
    "rufflet",
    "sandile",
    "sceptile",
    "scizor",
    "scolipede",
    "scorbunny",
    "scrafty",
    "scraggy",
    "scyther",
    "seviper",
    "sharpedo",
    "shiftry",
    "sirfetchd",
    "skarmory",
    "skorupi",
    "skuntank",
    "skwovet",
    "spearow",
    "spectrier",
    "stonjourner",
    "stunky",
    "swoobat",
    "tapukoko",
    "tauros",
    "thievul",
    "thundurus",
    "thundurus-therian",
    "thwackey",
    "togedemaru",
    "torchic",
    "tornadus",
    "tornadus-therian",
    "toxicroak",
    "treecko",
    "tyranitar",
    "tyrantrum",
    "tyrunt",
    "umbreon",
    "urshifu",
    "vespiquen",
    "vullaby",
    "weavile",
    "weezing",
    "weezing-galar",
    "wimpod",
    "woobat",
    "zacian",
    "zacian-crowned",
    "zapdos-galar",
    "zarude",
    "zarude-dada",
    "zeraora",
    "zigzagoon-galar",
    "zoroark",
    "zorua",
    "zubat",
    "zweilous"
  ],
  "desc": "Power doubles if the target has already taken damage this turn, other than direct damage from Belly Drum, confusion, Curse, or Pain Split.",
  "shortDesc": "Power doubles if target was damaged this turn."
}
